ss_utils_async/__init__.py
ss_utils_async-0.0.1.dist-info/METADATA
ss_utils_async-0.0.1.dist-info/WHEEL
ss_utils_async-0.0.1.dist-info/RECORD
